LICENSE
MANIFEST.in
README.md
pyproject.toml
setup.py
hapROH/__init__.py
hapROH/run.py
hapROH.egg-info/PKG-INFO
hapROH.egg-info/SOURCES.txt
hapROH.egg-info/dependency_links.txt
hapROH.egg-info/entry_points.txt
hapROH.egg-info/requires.txt
hapROH.egg-info/top_level.txt
hapsburg/__init__.py
hapsburg/cfunc.c
hapsburg/cfunc.pyx
hapsburg/emissions.py
hapsburg/emissions_lowmem.py
hapsburg/func.py
hapsburg/hapCONX.py
hapsburg/hapCon_ROH.py
hapsburg/hapROH_WGS.py
hapsburg/hmm_inference.py
hapsburg/postprocessing.py
hapsburg/preprocessing.py
hapsburg/preprocessing_lowmem.py
hapsburg/transitions.py
hapsburg/.ipynb_checkpoints/cfunc-checkpoint.pyx
hapsburg/PackagesSupport/__init__.py
hapsburg/PackagesSupport/fit_ne.py
hapsburg/PackagesSupport/hapsburg_run.py
hapsburg/PackagesSupport/pp_individual_roh_csvs.py
hapsburg/PackagesSupport/roh_expectations.py
hapsburg/PackagesSupport/simData.py
hapsburg/PackagesSupport/sqrt_scale.py
hapsburg/PackagesSupport/h5_python/__init__.py
hapsburg/PackagesSupport/h5_python/h5_functions.py
hapsburg/PackagesSupport/loadEigenstrat/__init__.py
hapsburg/PackagesSupport/loadEigenstrat/loadEigenstrat.py
hapsburg/PackagesSupport/loadEigenstrat/saveHDF5.py
hapsburg/PackagesSupport/parallel_runs/__init__.py
hapsburg/PackagesSupport/parallel_runs/helper_functions.py
hapsburg/figures/__init__.py
hapsburg/figures/plot_bars.py
hapsburg/figures/plot_ibdx.py
hapsburg/figures/plot_individual_roh.py
hapsburg/figures/plot_posterior.py
hapsburg/figures/plot_timelines.py