Metadata-Version: 2.4
Name: hapROH
Version: 0.70
Summary: Identify runs of homozygosity (hapROH) and contamination (hapCon) in ancient human DNA data
Author-email: Harald Ringbauer <harald_ringbauer@eva.mpg.de>, Yilei Huang <yilei_huang@eva.mpg.de>
Maintainer-email: Harald Ringbauer <harald_ringbauer@eva.mpg.de>
License-Expression: GPL-3.0-or-later
Project-URL: Documentation, https://haproh.readthedocs.io
Project-URL: Repository, https://github.com/hringbauer/hapROH
Keywords: ROH,ancient DNA,runs of homozygosity,consanguinity,aDNA contamination
Classifier: Programming Language :: Python :: 3
Classifier: Operating System :: OS Independent
Classifier: Development Status :: 5 - Production/Stable
Classifier: Topic :: Scientific/Engineering :: Bio-Informatics
Requires-Python: >=3.6
License-File: LICENSE
Requires-Dist: numpy
Requires-Dist: pandas
Requires-Dist: scipy
Requires-Dist: h5py
Requires-Dist: psutil
Requires-Dist: numdifftools
Provides-Extra: ne
Requires-Dist: statsmodels; extra == "ne"
Provides-Extra: fig
Requires-Dist: matplotlib; extra == "fig"
Dynamic: license-file
